gitsecret/__init__.py
tests/__init__.py
tests/unit/__init__.py
tests/unit/test_gitsecret_add.py
tests/unit/test_gitsecret_changes.py
tests/unit/test_gitsecret_clean.py
tests/unit/test_gitsecret_hide.py
tests/unit/test_gitsecret_init.py
tests/unit/test_gitsecret_killperson.py
tests/unit/test_gitsecret_list.py
tests/unit/test_gitsecret_remove.py
tests/unit/test_gitsecret_reveal.py
tests/unit/test_gitsecret_tell.py
tests/unit/test_gitsecret_whoknows.py
tests/utilities/__init__.py
tests/utilities/factories.py
tests/utilities/fixtures.py
gitsecret-0.1.0.dist-info/LICENSE.md
gitsecret-0.1.0.dist-info/METADATA
gitsecret-0.1.0.dist-info/WHEEL
gitsecret-0.1.0.dist-info/top_level.txt
gitsecret-0.1.0.dist-info/RECORD
