Metadata-Version: 2.1
Name: gitsecret
Version: 0.1.0
Summary: Python wrapper for git-secret.
Home-page: https://github.com/ivanklee86/gitsecret
Author: Ivan Lee
Author-email: ivanklee86@gmail.com
License: UNKNOWN
Platform: UNKNOWN
Classifier: Development Status :: 3 - Alpha
Classifier: Intended Audience :: Developers
Classifier: Topic :: Software Development :: Version Control :: Git
Classifier: Topic :: Security
Classifier: Topic :: Security :: Cryptography
Classifier: License :: OSI Approved :: MIT License
